{
  "paper_id": "apep_1299",
  "family_id": "apep_1299",
  "version": 1,
  "started_at": "2026-04-02T04:01:04.663513",
  "finished_at": "2026-04-02T04:42:46.954196",
  "total_seconds": 2502.29069,
  "phases": {
    "setup": {
      "started_at": "2026-04-02T04:01:04.663513",
      "finished_at": "2026-04-02T04:01:08.314673",
      "duration_seconds": 3.651168
    },
    "idea_selection": {
      "started_at": "2026-04-02T04:01:08.314673",
      "finished_at": "2026-04-02T04:07:18.550767",
      "duration_seconds": 370.236103
    },
    "execution": {
      "started_at": "2026-04-02T04:07:18.550767",
      "finished_at": "2026-04-02T04:38:59.854046",
      "duration_seconds": 1901.30329
    },
    "review": {
      "started_at": "2026-04-02T04:38:59.854046",
      "finished_at": "2026-04-02T04:42:39.177047",
      "duration_seconds": 219.323011
    },
    "publish": {
      "started_at": "2026-04-02T04:42:46.906436",
      "finished_at": "2026-04-02T04:42:46.954196",
      "duration_seconds": 0.047767
    }
  }
}
