{
  "paper_id": "apep_0780",
  "family_id": "apep_0780",
  "version": 1,
  "started_at": "2026-03-23T08:07:50.804657",
  "finished_at": "2026-03-23T08:41:29.243829",
  "total_seconds": 2018.439177,
  "phases": {
    "setup": {
      "started_at": "2026-03-23T08:07:50.804657",
      "finished_at": "2026-03-23T08:08:15.321776",
      "duration_seconds": 24.517124
    },
    "idea_selection": {
      "started_at": "2026-03-23T08:08:15.321776",
      "finished_at": "2026-03-23T08:08:24.834007",
      "duration_seconds": 9.512236
    },
    "execution": {
      "started_at": "2026-03-23T08:08:24.834007",
      "finished_at": "2026-03-23T08:38:10.236122",
      "duration_seconds": 1785.402121
    },
    "review": {
      "started_at": "2026-03-23T08:38:10.236122",
      "finished_at": "2026-03-23T08:41:07.931025",
      "duration_seconds": 177.694907
    },
    "publish": {
      "started_at": "2026-03-23T08:41:29.213884",
      "finished_at": "2026-03-23T08:41:29.243829",
      "duration_seconds": 0.02995
    }
  }
}
