{
  "paper_id": "apep_0602",
  "family_id": "apep_0602",
  "version": 1,
  "started_at": "2026-03-12T13:25:37.468504",
  "finished_at": "2026-03-12T14:38:25.786980",
  "total_seconds": 4368.318484,
  "phases": {
    "setup": {
      "started_at": "2026-03-12T13:25:37.468504",
      "finished_at": "2026-03-12T13:25:52.024049",
      "duration_seconds": 14.555551
    },
    "idea_selection": {
      "started_at": "2026-03-12T13:25:52.024049",
      "finished_at": "2026-03-12T13:26:25.380747",
      "duration_seconds": 33.356801
    },
    "execution": {
      "started_at": "2026-03-12T13:26:25.380747",
      "finished_at": "2026-03-12T14:29:41.486487",
      "duration_seconds": 3796.105757
    },
    "review": {
      "started_at": "2026-03-12T14:29:41.486487",
      "finished_at": "2026-03-12T14:38:19.647431",
      "duration_seconds": 518.161047
    },
    "publish": {
      "started_at": "2026-03-12T14:38:25.761697",
      "finished_at": "2026-03-12T14:38:25.786980",
      "duration_seconds": 0.025291
    }
  }
}
