{
  "iteration": 1,
  "max_iterations": 3,
  "proceed_to_phase4": true,
  "reason": "PURSUE idea found",
  "best_idea": {
    "rank": 1,
    "title": "The Metro Before the Metro: Construction-Phase Capitalization of Europe's Largest Transit Expansion",
    "score": 66,
    "recommendation": "PURSUE",
    "conditions": [
      "extending the pre-period as far back as possible",
      "reconstructing announcement/construction milestone dates",
      "not just opening dates",
      "making the paper explicitly about anticipation/construction timing rather than a generic transit ATE"
    ]
  },
  "timestamp": "2026-03-06T15:44:33.208891"
}