{
  "paper_id": "apep_0929",
  "family_id": "apep_0929",
  "version": 1,
  "started_at": "2026-03-25T13:32:57.475767",
  "finished_at": "2026-03-25T14:04:24.709493",
  "total_seconds": 1887.233734,
  "phases": {
    "setup": {
      "started_at": "2026-03-25T13:32:57.475767",
      "finished_at": "2026-03-25T13:33:20.527436",
      "duration_seconds": 23.051675
    },
    "idea_selection": {
      "started_at": "2026-03-25T13:33:20.527436",
      "finished_at": "2026-03-25T13:33:59.299760",
      "duration_seconds": 38.772331
    },
    "execution": {
      "started_at": "2026-03-25T13:33:59.299760",
      "finished_at": "2026-03-25T13:51:21.783159",
      "duration_seconds": 1042.483428
    },
    "review": {
      "started_at": "2026-03-25T13:51:21.783159",
      "finished_at": "2026-03-25T14:04:18.118530",
      "duration_seconds": 776.335378
    },
    "publish": {
      "started_at": "2026-03-25T14:04:24.681536",
      "finished_at": "2026-03-25T14:04:24.709493",
      "duration_seconds": 0.027965
    }
  }
}
