{
  "paper_id": "apep_0683",
  "family_id": "apep_0683",
  "version": 1,
  "started_at": "2026-03-14T16:57:16.664264",
  "finished_at": "2026-03-14T17:24:33.889245",
  "total_seconds": 1637.224987,
  "phases": {
    "setup": {
      "started_at": "2026-03-14T16:57:16.664264",
      "finished_at": "2026-03-14T16:57:37.909411",
      "duration_seconds": 21.24516
    },
    "idea_selection": {
      "started_at": "2026-03-14T16:57:37.909411",
      "finished_at": "2026-03-14T16:58:00.868515",
      "duration_seconds": 22.959113
    },
    "execution": {
      "started_at": "2026-03-14T16:58:00.868515",
      "finished_at": "2026-03-14T17:15:31.084207",
      "duration_seconds": 1050.215702
    },
    "review": {
      "started_at": "2026-03-14T17:15:31.084207",
      "finished_at": "2026-03-14T17:24:28.055257",
      "duration_seconds": 536.97106
    },
    "publish": {
      "started_at": "2026-03-14T17:24:33.864416",
      "finished_at": "2026-03-14T17:24:33.889245",
      "duration_seconds": 0.024835
    }
  }
}
