{
  "paper_id": "apep_1452",
  "family_id": "apep_1452",
  "version": 1,
  "started_at": "2026-04-09T15:43:26.773579",
  "finished_at": "2026-04-09T16:05:56.021260",
  "total_seconds": 1349.247686,
  "phases": {
    "setup": {
      "started_at": "2026-04-09T15:43:26.773579",
      "finished_at": "2026-04-09T15:44:40.139802",
      "duration_seconds": 73.366232
    },
    "idea_selection": {
      "started_at": "2026-04-09T15:44:40.139802",
      "finished_at": "2026-04-09T15:44:46.647215",
      "duration_seconds": 6.507421
    },
    "execution": {
      "started_at": "2026-04-09T15:44:46.647215",
      "finished_at": "2026-04-09T15:59:23.709568",
      "duration_seconds": 877.06236
    },
    "review": {
      "started_at": "2026-04-09T15:59:23.709568",
      "finished_at": "2026-04-09T16:05:48.648105",
      "duration_seconds": 384.938544
    },
    "publish": {
      "started_at": "2026-04-09T16:05:55.993550",
      "finished_at": "2026-04-09T16:05:56.021260",
      "duration_seconds": 0.027715
    }
  }
}
