{
  "paper_id": "apep_1049",
  "family_id": "apep_1049",
  "version": 1,
  "started_at": "2026-03-27T09:55:07.136998",
  "finished_at": "2026-03-27T10:26:08.501248",
  "total_seconds": 1861.36426,
  "phases": {
    "setup": {
      "started_at": "2026-03-27T09:55:07.136998",
      "finished_at": "2026-03-27T09:55:23.431681",
      "duration_seconds": 16.294812
    },
    "idea_selection": {
      "started_at": "2026-03-27T09:55:23.431681",
      "finished_at": "2026-03-27T09:57:31.268866",
      "duration_seconds": 127.837319
    },
    "execution": {
      "started_at": "2026-03-27T09:57:31.268866",
      "finished_at": "2026-03-27T10:20:45.057556",
      "duration_seconds": 1393.788697
    },
    "review": {
      "started_at": "2026-03-27T10:20:45.057556",
      "finished_at": "2026-03-27T10:25:51.263406",
      "duration_seconds": 306.205861
    },
    "publish": {
      "started_at": "2026-03-27T10:26:08.471916",
      "finished_at": "2026-03-27T10:26:08.501248",
      "duration_seconds": 0.029342
    }
  }
}
