{
  "paper_id": "apep_0920",
  "family_id": "apep_0920",
  "version": 1,
  "started_at": "2026-03-25T12:36:59.929923",
  "finished_at": "2026-03-25T13:13:29.164136",
  "total_seconds": 2189.234221,
  "phases": {
    "setup": {
      "started_at": "2026-03-25T12:36:59.929923",
      "finished_at": "2026-03-25T12:38:06.511511",
      "duration_seconds": 66.581599
    },
    "idea_selection": {
      "started_at": "2026-03-25T12:38:06.511511",
      "finished_at": "2026-03-25T12:38:27.961820",
      "duration_seconds": 21.450324
    },
    "execution": {
      "started_at": "2026-03-25T12:38:27.961820",
      "finished_at": "2026-03-25T13:01:54.314496",
      "duration_seconds": 1406.352684
    },
    "review": {
      "started_at": "2026-03-25T13:01:54.314496",
      "finished_at": "2026-03-25T13:13:22.220809",
      "duration_seconds": 687.90632
    },
    "publish": {
      "started_at": "2026-03-25T13:13:29.092034",
      "finished_at": "2026-03-25T13:13:29.164136",
      "duration_seconds": 0.07211
    }
  }
}
